<annotation>
	<folder></folder>
	<filename>ainex_img20240705_134815_996493_jpg.rf.863008e335dbc204bb20e5ded97af199.jpg</filename>
	<path>ainex_img20240705_134815_996493_jpg.rf.863008e335dbc204bb20e5ded97af199.jpg</path>
	<source>
		<database>roboflow.com</database>
	</source>
	<size>
		<width>640</width>
		<height>640</height>
		<depth>3</depth>
	</size>
	<segmented>0</segmented>
	<object>
		<name>ball</name>
		<pose>Unspecified</pose>
		<truncated>0</truncated>
		<difficult>0</difficult>
		<occluded>0</occluded>
		<bndbox>
			<xmin>111</xmin>
			<xmax>173</xmax>
			<ymin>322</ymin>
			<ymax>414</ymax>
		</bndbox>
	</object>
</annotation>
