<annotation>
	<folder></folder>
	<filename>ainex_img20240705_120226_553285_jpg.rf.eb28c8941df4ac4d154becb72ba05622.jpg</filename>
	<path>ainex_img20240705_120226_553285_jpg.rf.eb28c8941df4ac4d154becb72ba05622.jpg</path>
	<source>
		<database>roboflow.com</database>
	</source>
	<size>
		<width>640</width>
		<height>640</height>
		<depth>3</depth>
	</size>
	<segmented>0</segmented>
	<object>
		<name>ball</name>
		<pose>Unspecified</pose>
		<truncated>0</truncated>
		<difficult>0</difficult>
		<occluded>0</occluded>
		<bndbox>
			<xmin>170</xmin>
			<xmax>251</xmax>
			<ymin>476</ymin>
			<ymax>595</ymax>
		</bndbox>
	</object>
</annotation>
