<annotation>
	<folder></folder>
	<filename>ainex_img20240704_184403_153064_jpg.rf.4c80d2d83aa25413df5185bed274bc74.jpg</filename>
	<path>ainex_img20240704_184403_153064_jpg.rf.4c80d2d83aa25413df5185bed274bc74.jpg</path>
	<source>
		<database>roboflow.com</database>
	</source>
	<size>
		<width>640</width>
		<height>640</height>
		<depth>3</depth>
	</size>
	<segmented>0</segmented>
	<object>
		<name>ball</name>
		<pose>Unspecified</pose>
		<truncated>0</truncated>
		<difficult>0</difficult>
		<occluded>0</occluded>
		<bndbox>
			<xmin>259</xmin>
			<xmax>314</xmax>
			<ymin>28</ymin>
			<ymax>84</ymax>
		</bndbox>
	</object>
	<object>
		<name>ball</name>
		<pose>Unspecified</pose>
		<truncated>0</truncated>
		<difficult>0</difficult>
		<occluded>0</occluded>
		<bndbox>
			<xmin>209</xmin>
			<xmax>266</xmax>
			<ymin>53</ymin>
			<ymax>137</ymax>
		</bndbox>
	</object>
</annotation>
