<annotation>
	<folder></folder>
	<filename>ainex_img20240705_134945_861570_jpg.rf.3a4d956c4366548eb4e0e58aac34918f.jpg</filename>
	<path>ainex_img20240705_134945_861570_jpg.rf.3a4d956c4366548eb4e0e58aac34918f.jpg</path>
	<source>
		<database>roboflow.com</database>
	</source>
	<size>
		<width>640</width>
		<height>640</height>
		<depth>3</depth>
	</size>
	<segmented>0</segmented>
	<object>
		<name>ball</name>
		<pose>Unspecified</pose>
		<truncated>0</truncated>
		<difficult>0</difficult>
		<occluded>0</occluded>
		<bndbox>
			<xmin>171</xmin>
			<xmax>258</xmax>
			<ymin>513</ymin>
			<ymax>625</ymax>
		</bndbox>
	</object>
	<object>
		<name>ball</name>
		<pose>Unspecified</pose>
		<truncated>0</truncated>
		<difficult>0</difficult>
		<occluded>0</occluded>
		<bndbox>
			<xmin>55</xmin>
			<xmax>74</xmax>
			<ymin>110</ymin>
			<ymax>147</ymax>
		</bndbox>
	</object>
</annotation>
